Metadata-Version: 1.0
Name: xcode-releasemaker
Version: 0.1.0
Summary: Build tool to create releases in GitHub.
Home-page: http://lionheartsw.com/
Author: Dan Loewenherz
Author-email: dan@lionheartsw.com
License: Apache 2.0
Platform: UNKNOWN
